django_flowr-0.2.0.dist-info/DESCRIPTION.rst
django_flowr-0.2.0.dist-info/METADATA
django_flowr-0.2.0.dist-info/metadata.json
django_flowr-0.2.0.dist-info/RECORD
django_flowr-0.2.0.dist-info/top_level.txt
django_flowr-0.2.0.dist-info/WHEEL
flowr/__init__.py
flowr/admin.py
flowr/models.py
flowr/sample_rules.py
flowr/urls.py
flowr/views.py
flowr/migrations/0001_initial.py
flowr/migrations/__init__.py
flowr/static/flowr/css/.flowr.css.swp
flowr/static/flowr/css/flowr.css
flowr/static/flowr/js/cytoscape.min.js
flowr/static/flowr/js/w2ui-1.4.3.min.css
flowr/static/flowr/js/w2ui-1.4.3.min.js
flowr/templates/flowr/.edit_flow.html.swp
flowr/templates/flowr/base.html
flowr/templates/flowr/edit_flow.html
flowr/templates/flowr/graph.js
flowr/templates/flowr/header.html
flowr/templates/flowr/node_selected.html
flowr/templates/flowr/view_rules.html
flowr/tests/__init__.py
flowr/tests/models.py
flowr/tests/test_flow.py
flowr/tests/test_graph.py
